adc/__init__.py
adc/_align_widget.py
adc/_combine_widget.py
adc/_count_widget.py
adc/_manual_rois.py
adc/_prev_gdif_widget.py
adc/_progress_widget.py
adc/_projection_stack.py
adc/_reader.py
adc/_sample_data.py
adc/_segment_widget.py
adc/_split_stack.py
adc/_sub_stack.py
adc/_version.py
adc/align.py
adc/count.py
adc/fit.py
adc/io.py
adc/logging.conf
adc/merge.py
adc/napari.yaml
adc/plot.py
adc/tests/__init__.py
adc/tests/test_align.py
adc/tests/test_count.py
adc/tests/test_projection.py
adc/tests/test_reader.py
adc/tests/test_split.py
adc/tests/test_stack.py
adc/tests/test_substack.py
adc/tests/test_widgets.py
anchor_droplet_chip-0.5.0.dist-info/licenses/LICENSE
imreg_dft/__init__.py
imreg_dft/imreg.py
imreg_dft/utils.py
anchor_droplet_chip-0.5.0.dist-info/METADATA
anchor_droplet_chip-0.5.0.dist-info/WHEEL
anchor_droplet_chip-0.5.0.dist-info/entry_points.txt
anchor_droplet_chip-0.5.0.dist-info/top_level.txt
anchor_droplet_chip-0.5.0.dist-info/RECORD
