Metadata-Version: 2.4
Name: anchor-droplet-chip
Version: 0.5.0
Summary: Segment organoids and measure intensities
Home-page: https://github.com/BaroudLab/anchor-driplet-chip
Author: Andrey Aristov
Author-email: aaristov@pasteur.fr
License: BSD-3-Clause
Project-URL: Source Code, https://github.com/BaroudLab/anchor-droplet-chip
Classifier: Development Status :: 2 - Pre-Alpha
Classifier: Framework :: napari
Classifier: Intended Audience :: Developers
Classifier: License :: OSI Approved :: BSD License
Classifier: Operating System :: OS Independent
Classifier: Programming Language :: Python
Classifier: Programming Language :: Python :: 3
Classifier: Programming Language :: Python :: 3 :: Only
Classifier: Programming Language :: Python :: Implementation :: CPython
Classifier: Topic :: Software Development :: Testing
Requires-Python: >=3.8
License-File: LICENSE
Requires-Dist: dask
Requires-Dist: fire
Requires-Dist: h5py
Requires-Dist: jupyterlab
Requires-Dist: matplotlib
Requires-Dist: napari
Requires-Dist: nd2
Requires-Dist: numpy
Requires-Dist: pandas
Requires-Dist: pyqt6
Requires-Dist: pytest-qt
Requires-Dist: pyyaml
Requires-Dist: scikit-image
Requires-Dist: scipy
Requires-Dist: seaborn
Requires-Dist: tifffile
Requires-Dist: zarr-tools
Requires-Dist: zenodo-get
Dynamic: license-file
